README.md
setup.py
uber_cli/__init__.py
uber_cli/writers.py
uber_cli.egg-info/PKG-INFO
uber_cli.egg-info/SOURCES.txt
uber_cli.egg-info/dependency_links.txt
uber_cli.egg-info/entry_points.txt
uber_cli.egg-info/requires.txt
uber_cli.egg-info/top_level.txt