Metadata-Version: 1.1
Name: uber-cli
Version: 1.0.0
Summary: Unofficial read-only Uber CLI on top of uber-rides.
Home-page: https://github.com/strizhechenko/uber-cli
Author: Oleg Strizhechenko
Author-email: oleg.strizhechenko@gmail.com
License: MIT
Keywords: uber cli rides taxi util
Platform: UNKNOWN
Classifier: Development Status :: 3 - Alpha
Classifier: Intended Audience :: Developers
Classifier: Operating System :: MacOS
Classifier: Operating System :: POSIX
Classifier: Programming Language :: Python
Classifier: Programming Language :: Python :: 3
Classifier: Topic :: Software Development
Classifier: Topic :: Utilities
